notyourip/__init__.py
notyourip/core.py
notyourip-1.0.1.dist-info/licenses/LICENSE
notyourip-1.0.1.dist-info/METADATA
notyourip-1.0.1.dist-info/WHEEL
notyourip-1.0.1.dist-info/top_level.txt
notyourip-1.0.1.dist-info/RECORD
